{"action_map":{"20554339p.rfihub.com":{"dnt":false,"heuristicAction":"","nextUpdateTime":0,"userAction":"user_block"},"rfihub.com":
{"dnt":false,"heuristicAction":"","nextUpdateTime":0,"userAction":"user_block"},"163.com":
{"dnt":false,"heuristicAction":"","nextUpdateTime":0,"userAction":"user_block"},"1emn.com":
{"dnt":false,"heuristicAction":"","nextUpdateTime":0,"userAction":"user_block"},"2mdn.net":
{"dnt":false,"heuristicAction":"","nextUpdateTime":0,"userAction":"user_block"},"2o7.net":
{"dnt":false,"heuristicAction":"","nextUpdateTime":0,"userAction":"user_block"},"3lift.com":
{"dnt":false,"heuristicAction":"","nextUpdateTime":0,"userAction":"user_block"},"abtasty.com":
{"dnt":false,"heuristicAction":"","nextUpdateTime":0,"userAction":"user_block"},"activeconversion.com":
{"dnt":false,"heuristicAction":"","nextUpdateTime":0,"userAction":"user_block"},"adadvisor.net":
{"dnt":false,"heuristicAction":"","nextUpdateTime":0,"userAction":"user_block"},"adblade.com":
{"dnt":false,"heuristicAction":"","nextUpdateTime":0,"userAction":"user_block"},"adbrn.com":
{"dnt":false,"heuristicAction":"","nextUpdateTime":0,"userAction":"user_block"},"adbutler-tachyon.com":
{"dnt":false,"heuristicAction":"","nextUpdateTime":0,"userAction":"user_block"},"addthis.com":
{"dnt":false,"heuristicAction":"","nextUpdateTime":0,"userAction":"user_block"},"adsafeprotected.com":
{"dnt":false,"heuristicAction":"","nextUpdateTime":0,"userAction":"user_block"},"admantx.com":
{"dnt":false,"heuristicAction":"","nextUpdateTime":0,"userAction":"user_block"},"adamatic.co":
{"dnt":false,"heuristicAction":"","nextUpdateTime":0,"userAction":"user_block"},"adexchangeguru.com":
{"dnt":false,"heuristicAction":"","nextUpdateTime":0,"userAction":"user_block"},"adexchange.guru":
{"dnt":false,"heuristicAction":"","nextUpdateTime":0,"userAction":"user_block"},"adform.net":
{"dnt":false,"heuristicAction":"","nextUpdateTime":0,"userAction":"user_block"},"adform.com":
{"dnt":false,"heuristicAction":"","nextUpdateTime":0,"userAction":"user_block"},"adnxs.com":
{"dnt":false,"heuristicAction":"","nextUpdateTime":0,"userAction":"user_block"},"adrecover.com":
{"dnt":false,"heuristicAction":"","nextUpdateTime":0,"userAction":"user_block"},"adroll.com":
{"dnt":false,"heuristicAction":"","nextUpdateTime":0,"userAction":"user_block"},"ad-score.com":
{"dnt":false,"heuristicAction":"","nextUpdateTime":0,"userAction":"user_block"},"ads.yap.yahoo.com":
{"dnt":false,"heuristicAction":"","nextUpdateTime":0,"userAction":"user_block"},"adsrvr.org":
{"dnt":false,"heuristicAction":"","nextUpdateTime":0,"userAction":"user_block"},"adspsp.com":
{"dnt":false,"heuristicAction":"","nextUpdateTime":0,"userAction":"user_block"},"adsymptotic.com":
{"dnt":false,"heuristicAction":"","nextUpdateTime":0,"userAction":"user_block"},"ads.creative-serving.com":
{"dnt":false,"heuristicAction":"","nextUpdateTime":0,"userAction":"user_block"},"ads.freewheel.tv":
{"dnt":false,"heuristicAction":"","nextUpdateTime":0,"userAction":"user_block"},"ads.ndtv1.com":
{"dnt":false,"heuristicAction":"","nextUpdateTime":0,"userAction":"user_block"},"ads.servebom.com":
{"dnt":false,"heuristicAction":"","nextUpdateTime":0,"userAction":"user_block"},"ads.yahoo.com":
{"dnt":false,"heuristicAction":"","nextUpdateTime":0,"userAction":"user_block"},"ads-twitter.com":
{"dnt":false,"heuristicAction":"","nextUpdateTime":0,"userAction":"user_block"},"advertising.com":
{"dnt":false,"heuristicAction":"","nextUpdateTime":0,"userAction":"user_block"},"adtechus.com":
{"dnt":false,"heuristicAction":"","nextUpdateTime":0,"userAction":"user_block"},"adservex.media.net":
{"dnt":false,"heuristicAction":"","nextUpdateTime":0,"userAction":"user_block"},"adservice.google.com":
{"dnt":false,"heuristicAction":"","nextUpdateTime":0,"userAction":"user_block"},"adsys.townnews.com":
{"dnt":false,"heuristicAction":"","nextUpdateTime":0,"userAction":"user_block"},"alt.idgesg.net":
{"dnt":false,"heuristicAction":"","nextUpdateTime":0,"userAction":"user_block"},"alexametrics.com":
{"dnt":false,"heuristicAction":"","nextUpdateTime":0,"userAction":"user_block"},"alicdn.com":
{"dnt":false,"heuristicAction":"","nextUpdateTime":0,"userAction":"user_block"},"alooma.com":
{"dnt":false,"heuristicAction":"","nextUpdateTime":0,"userAction":"user_block"},"amazon-adsystem.com":
{"dnt":false,"heuristicAction":"","nextUpdateTime":0,"userAction":"user_block"},"analytics.apnewsregistry.com":
{"dnt":false,"heuristicAction":"","nextUpdateTime":0,"userAction":"user_block"},"analytics.aweber.com":
{"dnt":false,"heuristicAction":"","nextUpdateTime":0,"userAction":"user_block"},"analytics.cohesionapps.com":
{"dnt":false,"heuristicAction":"","nextUpdateTime":0,"userAction":"user_block"},"analytics.edgekey.net":
{"dnt":false,"heuristicAction":"","nextUpdateTime":0,"userAction":"user_block"},"analytics.edgesuite.net":
{"dnt":false,"heuristicAction":"","nextUpdateTime":0,"userAction":"user_block"},"analytics.kaltura.com":
{"dnt":false,"heuristicAction":"","nextUpdateTime":0,"userAction":"user_block"},"analytics.newsinc.com":
{"dnt":false,"heuristicAction":"","nextUpdateTime":0,"userAction":"user_block"},"analytics.posttv.com":
{"dnt":false,"heuristicAction":"","nextUpdateTime":0,"userAction":"user_block"},"analytics.tout.com":
{"dnt":false,"heuristicAction":"","nextUpdateTime":0,"userAction":"user_block"},"analytics.twitter.com":
{"dnt":false,"heuristicAction":"","nextUpdateTime":0,"userAction":"user_block"},"analytics.yahoo.com":
{"dnt":false,"heuristicAction":"","nextUpdateTime":0,"userAction":"user_block"},"ape-asset-tag.timeinc.com":
{"dnt":false,"heuristicAction":"","nextUpdateTime":0,"userAction":"user_block"},"api.pinterest.com":
{"dnt":false,"heuristicAction":"","nextUpdateTime":0,"userAction":"user_block"},"atdmt.com":
{"dnt":false,"heuristicAction":"","nextUpdateTime":0,"userAction":"user_block"},"assets.adobedtm.com":
{"dnt":false,"heuristicAction":"","nextUpdateTime":0,"userAction":"user_block"},"assets.vidora.com":
{"dnt":false,"heuristicAction":"","nextUpdateTime":0,"userAction":"user_block"},"assoc-amazon.com":
{"dnt":false,"heuristicAction":"","nextUpdateTime":0,"userAction":"user_block"},"atwola.com":
{"dnt":false,"heuristicAction":"","nextUpdateTime":0,"userAction":"user_block"},"audienceinsights.net":
{"dnt":false,"heuristicAction":"","nextUpdateTime":0,"userAction":"user_block"},"augur.io":
{"dnt":false,"heuristicAction":"","nextUpdateTime":0,"userAction":"user_block"},"authorize.coxmediagroup.com":
{"dnt":false,"heuristicAction":"","nextUpdateTime":0,"userAction":"user_block"},"ayads.co":
{"dnt":false,"heuristicAction":"","nextUpdateTime":0,"userAction":"user_block"},"bat.bing.com":
{"dnt":false,"heuristicAction":"","nextUpdateTime":0,"userAction":"user_block"},"bazaarvoice.com":
{"dnt":false,"heuristicAction":"","nextUpdateTime":0,"userAction":"user_block"},"beacon.deseretconnect.com":
{"dnt":false,"heuristicAction":"","nextUpdateTime":0,"userAction":"user_block"},"beacon.walmart.com":
{"dnt":false,"heuristicAction":"","nextUpdateTime":0,"userAction":"user_block"},"betrad.com":
{"dnt":false,"heuristicAction":"","nextUpdateTime":0,"userAction":"user_block"},"biddr.brealtime.com":
{"dnt":false,"heuristicAction":"","nextUpdateTime":0,"userAction":"user_block"},"bitmedia.io":
{"dnt":false,"heuristicAction":"","nextUpdateTime":0,"userAction":"user_block"},"bkrtx.com":
{"dnt":false,"heuristicAction":"","nextUpdateTime":0,"userAction":"user_block"},"blueconic.com":
{"dnt":false,"heuristicAction":"","nextUpdateTime":0,"userAction":"user_block"},"bluekai.com":
{"dnt":false,"heuristicAction":"","nextUpdateTime":0,"userAction":"user_block"},"boo-box.com":
{"dnt":false,"heuristicAction":"","nextUpdateTime":0,"userAction":"user_block"},"bouncex.net":
{"dnt":false,"heuristicAction":"","nextUpdateTime":0,"userAction":"user_block"},"bounceexchange.com":
{"dnt":false,"heuristicAction":"","nextUpdateTime":0,"userAction":"user_block"},"btrll.com":
{"dnt":false,"heuristicAction":"","nextUpdateTime":0,"userAction":"user_block"},"budgetedbauer.com":
{"dnt":false,"heuristicAction":"","nextUpdateTime":0,"userAction":"user_block"},"burnside.dtcn.com":
{"dnt":false,"heuristicAction":"","nextUpdateTime":0,"userAction":"user_block"},"buysellads.net":
{"dnt":false,"heuristicAction":"","nextUpdateTime":0,"userAction":"user_block"},"c.bing.com":
{"dnt":false,"heuristicAction":"","nextUpdateTime":0,"userAction":"user_block"},"c.newsinc.com":
{"dnt":false,"heuristicAction":"","nextUpdateTime":0,"userAction":"user_block"},"capture.condenastdigital.com":
{"dnt":false,"heuristicAction":"","nextUpdateTime":0,"userAction":"user_block"},"carambo.la":
{"dnt":false,"heuristicAction":"","nextUpdateTime":0,"userAction":"user_block"},"casalemedia.com":
{"dnt":false,"heuristicAction":"","nextUpdateTime":0,"userAction":"user_block"},"cdn-social.janrain.com":
{"dnt":false,"heuristicAction":"","nextUpdateTime":0,"userAction":"user_block"},"cdn.at.atwola.com":
{"dnt":false,"heuristicAction":"","nextUpdateTime":0,"userAction":"user_block"},"cdn-net.com":
{"dnt":false,"heuristicAction":"","nextUpdateTime":0,"userAction":"user_block"},"cdn.boomtrain.com":
{"dnt":false,"heuristicAction":"","nextUpdateTime":0,"userAction":"user_block"},"cdn.carbonads.com":
{"dnt":false,"heuristicAction":"","nextUpdateTime":0,"userAction":"user_block"},"cdn.digitru.st":
{"dnt":false,"heuristicAction":"","nextUpdateTime":0,"userAction":"user_block"},"cdn.engine.4dsply.com":
{"dnt":false,"heuristicAction":"","nextUpdateTime":0,"userAction":"user_block"},"cdn.engine.addroplet.com":
{"dnt":false,"heuristicAction":"","nextUpdateTime":0,"userAction":"user_block"},"cdn.gotraffic.net":
{"dnt":false,"heuristicAction":"","nextUpdateTime":0,"userAction":"user_block"},"cdn.krxd.net":
{"dnt":false,"heuristicAction":"","nextUpdateTime":0,"userAction":"user_block"},"cdn.yldbt.com":
{"dnt":false,"heuristicAction":"","nextUpdateTime":0,"userAction":"user_block"},"chartbeat.com":
{"dnt":false,"heuristicAction":"","nextUpdateTime":0,"userAction":"user_block"},"chartbeat.net":
{"dnt":false,"heuristicAction":"","nextUpdateTime":0,"userAction":"user_block"},"clickability.com":
{"dnt":false,"heuristicAction":"","nextUpdateTime":0,"userAction":"user_block"},"comments-api.ext.nile.works":
{"dnt":false,"heuristicAction":"","nextUpdateTime":0,"userAction":"user_block"},"config.lrcontent.com":
{"dnt":false,"heuristicAction":"","nextUpdateTime":0,"userAction":"user_block"},"content-ad.net":
{"dnt":false,"heuristicAction":"","nextUpdateTime":0,"userAction":"user_block"},"contentsquare.net":
{"dnt":false,"heuristicAction":"","nextUpdateTime":0,"userAction":"user_block"},"contextual.media.net":
{"dnt":false,"heuristicAction":"","nextUpdateTime":0,"userAction":"user_block"},"contextweb.com":
{"dnt":false,"heuristicAction":"","nextUpdateTime":0,"userAction":"user_block"},"cookiex.ngd.yahoo.com":
{"dnt":false,"heuristicAction":"","nextUpdateTime":0,"userAction":"user_block"},"counter.scribblelive.com":
{"dnt":false,"heuristicAction":"","nextUpdateTime":0,"userAction":"user_block"},"counter.snackly.co":
{"dnt":false,"heuristicAction":"","nextUpdateTime":0,"userAction":"user_block"},"criteo.com":
{"dnt":false,"heuristicAction":"","nextUpdateTime":0,"userAction":"user_block"},"crwdcntrl.net":
{"dnt":false,"heuristicAction":"","nextUpdateTime":0,"userAction":"user_block"},"cse.google.com":
{"dnt":false,"heuristicAction":"","nextUpdateTime":0,"userAction":"user_block"},"csi.gstatic.com":
{"dnt":false,"heuristicAction":"","nextUpdateTime":0,"userAction":"user_block"},"cxense.com":
{"dnt":false,"heuristicAction":"","nextUpdateTime":0,"userAction":"user_block"},"cnzz.com":
{"dnt":false,"heuristicAction":"","nextUpdateTime":0,"userAction":"user_block"},"d13im3ek7neeqp.cloudfront.net":
{"dnt":false,"heuristicAction":"","nextUpdateTime":0,"userAction":"user_block"},"d1azc1qln24ryf.cloudfront.net":
{"dnt":false,"heuristicAction":"","nextUpdateTime":0,"userAction":"user_block"},"d1g3gvqfdsvkse.cloudfront.net":
{"dnt":false,"heuristicAction":"","nextUpdateTime":0,"userAction":"user_block"},"d1mqe0bl913lpg.cloudfront.net":
{"dnt":false,"heuristicAction":"","nextUpdateTime":0,"userAction":"user_block"},"d28ethi6slcjbm.cloudfront.net":
{"dnt":false,"heuristicAction":"","nextUpdateTime":0,"userAction":"user_block"},"d2ha22j8ys3e0o.cloudfront.net":
{"dnt":false,"heuristicAction":"","nextUpdateTime":0,"userAction":"user_block"},"d2uevgmgh16uk4.cloudfront.net":
{"dnt":false,"heuristicAction":"","nextUpdateTime":0,"userAction":"user_block"},"d2ymkpxi1rgldj.cloudfront.net":
{"dnt":false,"heuristicAction":"","nextUpdateTime":0,"userAction":"user_block"},"d31qbv1cthcecs.cloudfront.net":
{"dnt":false,"heuristicAction":"","nextUpdateTime":0,"userAction":"user_block"},"d37sfqor0g25ph.cloudfront.net":
{"dnt":false,"heuristicAction":"","nextUpdateTime":0,"userAction":"user_block"},"d38nbbai6u794i.cloudfront.net":
{"dnt":false,"heuristicAction":"","nextUpdateTime":0,"userAction":"user_block"},"d3m83gvgzupli.cloudfront.net":
{"dnt":false,"heuristicAction":"","nextUpdateTime":0,"userAction":"user_block"},"d5nxst8fruw4z.cloudfront.net":
{"dnt":false,"heuristicAction":"","nextUpdateTime":0,"userAction":"user_block"},"d1z2jf7jlzjs58.cloudfront.net":
{"dnt":false,"heuristicAction":"","nextUpdateTime":0,"userAction":"user_block"},"d21rhj7n383afu.cloudfront.net":
{"dnt":false,"heuristicAction":"","nextUpdateTime":0,"userAction":"user_block"},"d2c8v52ll5s99u.cloudfront.net":
{"dnt":false,"heuristicAction":"","nextUpdateTime":0,"userAction":"user_block"},"d2x3bkdslnxkuj.cloudfront.net":
{"dnt":false,"heuristicAction":"","nextUpdateTime":0,"userAction":"user_block"},"d2ylgh2cnbot5i.cloudfront.net":
{"dnt":false,"heuristicAction":"","nextUpdateTime":0,"userAction":"user_block"},"d3c3cq33003psk.cloudfront.net":
{"dnt":false,"heuristicAction":"","nextUpdateTime":0,"userAction":"user_block"},"d8rk54i4mohrb.cloudfront.net":
{"dnt":false,"heuristicAction":"","nextUpdateTime":0,"userAction":"user_block"},"deow9bq0xqvbj.cloudfront.net":
{"dnt":false,"heuristicAction":"","nextUpdateTime":0,"userAction":"user_block"},"dff7tx5c2qbxc.cloudfront.net":
{"dnt":false,"heuristicAction":"","nextUpdateTime":0,"userAction":"user_block"},"dnkzzz1hlto79.cloudfront.net":
{"dnt":false,"heuristicAction":"","nextUpdateTime":0,"userAction":"user_block"},"dp8hsntg6do36.cloudfront.net":
{"dnt":false,"heuristicAction":"","nextUpdateTime":0,"userAction":"user_block"},"dwgyu36up6iuz.cloudfront.net":
{"dnt":false,"heuristicAction":"","nextUpdateTime":0,"userAction":"user_block"},"d.agkn.com":
{"dnt":false,"heuristicAction":"","nextUpdateTime":0,"userAction":"user_block"},"demdex.net":
{"dnt":false,"heuristicAction":"","nextUpdateTime":0,"userAction":"user_block"},"demandbase.com":
{"dnt":false,"heuristicAction":"","nextUpdateTime":0,"userAction":"user_block"},"deployads.com":
{"dnt":false,"heuristicAction":"","nextUpdateTime":0,"userAction":"user_block"},"device.maxmind.com":
{"dnt":false,"heuristicAction":"","nextUpdateTime":0,"userAction":"user_block"},"dianomi.com":
{"dnt":false,"heuristicAction":"","nextUpdateTime":0,"userAction":"user_block"},"distiltag.com":
{"dnt":false,"heuristicAction":"","nextUpdateTime":0,"userAction":"user_block"},"dmtracker.com":
{"dnt":false,"heuristicAction":"","nextUpdateTime":0,"userAction":"user_block"},"drift.com":
{"dnt":false,"heuristicAction":"","nextUpdateTime":0,"userAction":"user_block"},"doubleclick.net":
{"dnt":false,"heuristicAction":"","nextUpdateTime":0,"userAction":"user_block"},"doubleverify.com":
{"dnt":false,"heuristicAction":"","nextUpdateTime":0,"userAction":"user_block"},"dynamicyield.com":
{"dnt":false,"heuristicAction":"","nextUpdateTime":0,"userAction":"user_block"},"ece-logger.nandomedia.com":
{"dnt":false,"heuristicAction":"","nextUpdateTime":0,"userAction":"user_block"},"edge.quantserve.com":
{"dnt":false,"heuristicAction":"","nextUpdateTime":0,"userAction":"user_block"},"edigitalsurvey.com":
{"dnt":false,"heuristicAction":"","nextUpdateTime":0,"userAction":"user_block"},"effectivemeasure.net":
{"dnt":false,"heuristicAction":"","nextUpdateTime":0,"userAction":"user_block"},"en25.com":
{"dnt":false,"heuristicAction":"","nextUpdateTime":0,"userAction":"user_block"},"ensighten.com":
{"dnt":false,"heuristicAction":"","nextUpdateTime":0,"userAction":"user_block"},"eu-services.babator.com":
{"dnt":false,"heuristicAction":"","nextUpdateTime":0,"userAction":"user_block"},"exelator.com":
{"dnt":false,"heuristicAction":"","nextUpdateTime":0,"userAction":"user_block"},"eyenewton.ru":
{"dnt":false,"heuristicAction":"","nextUpdateTime":0,"userAction":"user_block"},"eyereturn.com":
{"dnt":false,"heuristicAction":"","nextUpdateTime":0,"userAction":"user_block"},"facebook.com":
{"dnt":false,"heuristicAction":"","nextUpdateTime":0,"userAction":"user_block"},"facebook.net":
{"dnt":false,"heuristicAction":"","nextUpdateTime":0,"userAction":"user_block"},"fallingfalcon.com":
{"dnt":false,"heuristicAction":"","nextUpdateTime":0,"userAction":"user_block"},"fbcdn.net":
{"dnt":false,"heuristicAction":"","nextUpdateTime":0,"userAction":"user_block"},"fbsbx.com":
{"dnt":false,"heuristicAction":"","nextUpdateTime":0,"userAction":"user_block"},"fdlstatic.com":
{"dnt":false,"heuristicAction":"","nextUpdateTime":0,"userAction":"user_block"},"firebaseio.com":
{"dnt":false,"heuristicAction":"","nextUpdateTime":0,"userAction":"user_block"},"firstimpression.io":
{"dnt":false,"heuristicAction":"","nextUpdateTime":0,"userAction":"user_block"},"foresee.com":
{"dnt":false,"heuristicAction":"","nextUpdateTime":0,"userAction":"user_block"},"fqtag.com":
{"dnt":false,"heuristicAction":"","nextUpdateTime":0,"userAction":"user_block"},"freegeoip.net":
{"dnt":false,"heuristicAction":"","nextUpdateTime":0,"userAction":"user_block"},"fullstory.com":
{"dnt":false,"heuristicAction":"","nextUpdateTime":0,"userAction":"user_block"},"fwmrm.net":
{"dnt":false,"heuristicAction":"","nextUpdateTime":0,"userAction":"user_block"},"gads.pubmatic.com":
{"dnt":false,"heuristicAction":"","nextUpdateTime":0,"userAction":"user_block"},"geo.yahoo.com":
{"dnt":false,"heuristicAction":"","nextUpdateTime":0,"userAction":"user_block"},"geoservice.curse.com":
{"dnt":false,"heuristicAction":"","nextUpdateTime":0,"userAction":"user_block"},"getclicky.com":
{"dnt":false,"heuristicAction":"","nextUpdateTime":0,"userAction":"user_block"},"gigya.com":
{"dnt":false,"heuristicAction":"","nextUpdateTime":0,"userAction":"user_block"},"globalwebindex.net":
{"dnt":false,"heuristicAction":"","nextUpdateTime":0,"userAction":"user_block"},"go-mpulse.net":
{"dnt":false,"heuristicAction":"","nextUpdateTime":0,"userAction":"user_block"},"google-analytics.com":
{"dnt":false,"heuristicAction":"","nextUpdateTime":0,"userAction":"user_block"},"googleadservices.com":
{"dnt":false,"heuristicAction":"","nextUpdateTime":0,"userAction":"user_block"},"googletagmanager.com":
{"dnt":false,"heuristicAction":"","nextUpdateTime":0,"userAction":"user_block"},"googletagservices.com":
{"dnt":false,"heuristicAction":"","nextUpdateTime":0,"userAction":"user_block"},"gwallet.com":
{"dnt":false,"heuristicAction":"","nextUpdateTime":0,"userAction":"user_block"},"heapanalytics.com":
{"dnt":false,"heuristicAction":"","nextUpdateTime":0,"userAction":"user_block"},"hlserve.com":
{"dnt":false,"heuristicAction":"","nextUpdateTime":0,"userAction":"user_block"},"hotjar.com":
{"dnt":false,"heuristicAction":"","nextUpdateTime":0,"userAction":"user_block"},"hubspot.com":
{"dnt":false,"heuristicAction":"","nextUpdateTime":0,"userAction":"user_block"},"hwcdn.net":
{"dnt":false,"heuristicAction":"","nextUpdateTime":0,"userAction":"user_block"},"i10c.net":
{"dnt":false,"heuristicAction":"","nextUpdateTime":0,"userAction":"user_block"},"idealmedia.com":
{"dnt":false,"heuristicAction":"","nextUpdateTime":0,"userAction":"user_block"},"idgesg.net":
{"dnt":false,"heuristicAction":"","nextUpdateTime":0,"userAction":"user_block"},"imrworldwide.com":
{"dnt":false,"heuristicAction":"","nextUpdateTime":0,"userAction":"user_block"},"infinityid.condenastdigital.com":
{"dnt":false,"heuristicAction":"","nextUpdateTime":0,"userAction":"user_block"},"inq.com":
{"dnt":false,"heuristicAction":"","nextUpdateTime":0,"userAction":"user_block"},"intentiq.com":
{"dnt":false,"heuristicAction":"","nextUpdateTime":0,"userAction":"user_block"},"js-sec.indexww.com":
{"dnt":false,"heuristicAction":"","nextUpdateTime":0,"userAction":"user_block"},"js.appboycdn.com":
{"dnt":false,"heuristicAction":"","nextUpdateTime":0,"userAction":"user_block"},"js.hs-analytics.net":
{"dnt":false,"heuristicAction":"","nextUpdateTime":0,"userAction":"user_block"},"js.hs-scripts.com":
{"dnt":false,"heuristicAction":"","nextUpdateTime":0,"userAction":"user_block"},"js.hscta.net":
{"dnt":false,"heuristicAction":"","nextUpdateTime":0,"userAction":"user_block"},"js.hsforms.net":
{"dnt":false,"heuristicAction":"","nextUpdateTime":0,"userAction":"user_block"},"js.hsleadflows.net":
{"dnt":false,"heuristicAction":"","nextUpdateTime":0,"userAction":"user_block"},"jsrdn.com":
{"dnt":false,"heuristicAction":"","nextUpdateTime":0,"userAction":"user_block"},"instinctiveads.com":
{"dnt":false,"heuristicAction":"","nextUpdateTime":0,"userAction":"user_block"},"js.moatads.com":
{"dnt":false,"heuristicAction":"","nextUpdateTime":0,"userAction":"user_block"},"keen.io":
{"dnt":false,"heuristicAction":"","nextUpdateTime":0,"userAction":"user_block"},"kissmetrics.com":
{"dnt":false,"heuristicAction":"","nextUpdateTime":0,"userAction":"user_block"},"klaviyo.com":
{"dnt":false,"heuristicAction":"","nextUpdateTime":0,"userAction":"user_block"},"krxd.net":
{"dnt":false,"heuristicAction":"","nextUpdateTime":0,"userAction":"user_block"},"kxcdn.com":     
{"dnt":false,"heuristicAction":"","nextUpdateTime":0,"userAction":"user_block"},"launch.newsinc.com":
{"dnt":false,"heuristicAction":"","nextUpdateTime":0,"userAction":"user_block"},"lduhtrp.net":
{"dnt":false,"heuristicAction":"","nextUpdateTime":0,"userAction":"user_block"},"lijit.com":
{"dnt":false,"heuristicAction":"","nextUpdateTime":0,"userAction":"user_block"},"linkedin.com":
{"dnt":false,"heuristicAction":"","nextUpdateTime":0,"userAction":"user_block"},"litix.io":
{"dnt":false,"heuristicAction":"","nextUpdateTime":0,"userAction":"user_block"},"liverail.com":
{"dnt":false,"heuristicAction":"","nextUpdateTime":0,"userAction":"user_block"},"lrcdn.net":
{"dnt":false,"heuristicAction":"","nextUpdateTime":0,"userAction":"user_block"},"lrcontent.com":
{"dnt":false,"heuristicAction":"","nextUpdateTime":0,"userAction":"user_block"},"logger.snackly.co":
{"dnt":false,"heuristicAction":"","nextUpdateTime":0,"userAction":"user_block"},"magnuum.com":
{"dnt":false,"heuristicAction":"","nextUpdateTime":0,"userAction":"user_block"},"marketingautomation.services":
{"dnt":false,"heuristicAction":"","nextUpdateTime":0,"userAction":"user_block"},"marketo.com":
{"dnt":false,"heuristicAction":"","nextUpdateTime":0,"userAction":"user_block"},"mathtag.com":
{"dnt":false,"heuristicAction":"","nextUpdateTime":0,"userAction":"user_block"},"matheranalytics.com":
{"dnt":false,"heuristicAction":"","nextUpdateTime":0,"userAction":"user_block"},"maxmind.com":
{"dnt":false,"heuristicAction":"","nextUpdateTime":0,"userAction":"user_block"},"metric.gstatic.com":
{"dnt":false,"heuristicAction":"","nextUpdateTime":0,"userAction":"user_block"},"metrics.brightcove.com":
{"dnt":false,"heuristicAction":"","nextUpdateTime":0,"userAction":"user_block"},"mg2connext.com":
{"dnt":false,"heuristicAction":"","nextUpdateTime":0,"userAction":"user_block"},"moatads.com":
{"dnt":false,"heuristicAction":"","nextUpdateTime":0,"userAction":"user_block"},"monetate.net":
{"dnt":false,"heuristicAction":"","nextUpdateTime":0,"userAction":"user_block"},"monetate.com":
{"dnt":false,"heuristicAction":"","nextUpdateTime":0,"userAction":"user_block"},"mkt61.net":
{"dnt":false,"heuristicAction":"","nextUpdateTime":0,"userAction":"user_block"},"mstrlytcs.com":
{"dnt":false,"heuristicAction":"","nextUpdateTime":0,"userAction":"user_block"},"murdoog.com":
{"dnt":false,"heuristicAction":"","nextUpdateTime":0,"userAction":"user_block"},"mux.com":
{"dnt":false,"heuristicAction":"","nextUpdateTime":0,"userAction":"user_block"},"mxpnl.com":
{"dnt":false,"heuristicAction":"","nextUpdateTime":0,"userAction":"user_block"},"nbcudigitaladops.com":
{"dnt":false,"heuristicAction":"","nextUpdateTime":0,"userAction":"user_block"},"nebula-cdn.kampyle.com":
{"dnt":false,"heuristicAction":"","nextUpdateTime":0,"userAction":"user_block"},"nervoussummer.com":
{"dnt":false,"heuristicAction":"","nextUpdateTime":0,"userAction":"user_block"},"newrelic.com":
{"dnt":false,"heuristicAction":"","nextUpdateTime":0,"userAction":"user_block"},"nextage.com":
{"dnt":false,"heuristicAction":"","nextUpdateTime":0,"userAction":"user_block"},"nfltags.com":
{"dnt":false,"heuristicAction":"","nextUpdateTime":0,"userAction":"user_block"},"npttech.com":
{"dnt":false,"heuristicAction":"","nextUpdateTime":0,"userAction":"user_block"},"nr-data.net":
{"dnt":false,"heuristicAction":"","nextUpdateTime":0,"userAction":"user_block"},"openx.net":
{"dnt":false,"heuristicAction":"","nextUpdateTime":0,"userAction":"user_block"},"omnitagjs.com":
{"dnt":false,"heuristicAction":"","nextUpdateTime":0,"userAction":"user_block"},"omtrdc.net":
{"dnt":false,"heuristicAction":"","nextUpdateTime":0,"userAction":"user_block"},"onesignal.com":
{"dnt":false,"heuristicAction":"","nextUpdateTime":0,"userAction":"user_block"},"onetag.com":
{"dnt":false,"heuristicAction":"","nextUpdateTime":0,"userAction":"user_block"},"optimizely.com":
{"dnt":false,"heuristicAction":"","nextUpdateTime":0,"userAction":"user_block"},"optimize-stats.voxmedia.com":
{"dnt":false,"heuristicAction":"","nextUpdateTime":0,"userAction":"user_block"},"outbrain.com":
{"dnt":false,"heuristicAction":"","nextUpdateTime":0,"userAction":"user_block"},"pagead2.googlesyndication.com":
{"dnt":false,"heuristicAction":"","nextUpdateTime":0,"userAction":"user_block"},"pagefair.com":
{"dnt":false,"heuristicAction":"","nextUpdateTime":0,"userAction":"user_block"},"pagefair.net":
{"dnt":false,"heuristicAction":"","nextUpdateTime":0,"userAction":"user_block"},"pardot.com":
{"dnt":false,"heuristicAction":"","nextUpdateTime":0,"userAction":"user_block"},"perfectmarket.com":
{"dnt":false,"heuristicAction":"","nextUpdateTime":0,"userAction":"user_block"},"petametrics.com":
{"dnt":false,"heuristicAction":"","nextUpdateTime":0,"userAction":"user_block"},"p.typekit.net":
{"dnt":false,"heuristicAction":"","nextUpdateTime":0,"userAction":"user_block"},"pix.nbcuni.com":
{"dnt":false,"heuristicAction":"","nextUpdateTime":0,"userAction":"user_block"},"pixel.condenastdigital.com":
{"dnt":false,"heuristicAction":"","nextUpdateTime":0,"userAction":"user_block"},"pixel.keywee.co":
{"dnt":false,"heuristicAction":"","nextUpdateTime":0,"userAction":"user_block"},"pixel.nc0.co":
{"dnt":false,"heuristicAction":"","nextUpdateTime":0,"userAction":"user_block"},"pixel.quantserve.com":
{"dnt":false,"heuristicAction":"","nextUpdateTime":0,"userAction":"user_block"},"pixel.watch":
{"dnt":false,"heuristicAction":"","nextUpdateTime":0,"userAction":"user_block"},"pixel.wp.com":
{"dnt":false,"heuristicAction":"","nextUpdateTime":0,"userAction":"user_block"},"platform.instagram.com":
{"dnt":false,"heuristicAction":"","nextUpdateTime":0,"userAction":"user_block"},"plista.com":
{"dnt":false,"heuristicAction":"","nextUpdateTime":0,"userAction":"user_block"},"plugin.mediavoice.com":
{"dnt":false,"heuristicAction":"","nextUpdateTime":0,"userAction":"user_block"},"pro-market.net":
{"dnt":false,"heuristicAction":"","nextUpdateTime":0,"userAction":"user_block"},"pubmatic.com":
{"dnt":false,"heuristicAction":"","nextUpdateTime":0,"userAction":"user_block"},"pusher.com":
{"dnt":false,"heuristicAction":"","nextUpdateTime":0,"userAction":"user_block"},"pushwoosh.com":
{"dnt":false,"heuristicAction":"","nextUpdateTime":0,"userAction":"user_block"},"pushcrew.com":
{"dnt":false,"heuristicAction":"","nextUpdateTime":0,"userAction":"user_block"},"pxi.pub":
{"dnt":false,"heuristicAction":"","nextUpdateTime":0,"userAction":"user_block"},"qualtrics.com":
{"dnt":false,"heuristicAction":"","nextUpdateTime":0,"userAction":"user_block"},"qubit.com":
{"dnt":false,"heuristicAction":"","nextUpdateTime":0,"userAction":"user_block"},"rackcdn.com":
{"dnt":false,"heuristicAction":"","nextUpdateTime":0,"userAction":"user_block"},"radar.cedexis.com":
{"dnt":false,"heuristicAction":"","nextUpdateTime":0,"userAction":"user_block"},"realvu.com":
{"dnt":false,"heuristicAction":"","nextUpdateTime":0,"userAction":"user_block"},"realvu.net":
{"dnt":false,"heuristicAction":"","nextUpdateTime":0,"userAction":"user_block"},"rfihub.com":
{"dnt":false,"heuristicAction":"","nextUpdateTime":0,"userAction":"user_block"},"rfihub.net":
{"dnt":false,"heuristicAction":"","nextUpdateTime":0,"userAction":"user_block"},"richrelevance.com":
{"dnt":false,"heuristicAction":"","nextUpdateTime":0,"userAction":"user_block"},"rlcdn.com":
{"dnt":false,"heuristicAction":"","nextUpdateTime":0,"userAction":"user_block"},"roosterfirework.com":
{"dnt":false,"heuristicAction":"","nextUpdateTime":0,"userAction":"user_block"},"rpxnow.com":
{"dnt":false,"heuristicAction":"","nextUpdateTime":0,"userAction":"user_block"},"rtk.io":
{"dnt":false,"heuristicAction":"","nextUpdateTime":0,"userAction":"user_block"},"ru4.com":
{"dnt":false,"heuristicAction":"","nextUpdateTime":0,"userAction":"user_block"},"ruamupr.com":
{"dnt":false,"heuristicAction":"","nextUpdateTime":0,"userAction":"user_block"},"rubiconproject.com":
{"dnt":false,"heuristicAction":"","nextUpdateTime":0,"userAction":"user_block"},"s.go-mpulse.net":
{"dnt":false,"heuristicAction":"","nextUpdateTime":0,"userAction":"user_block"},"s.gweini.com":
{"dnt":false,"heuristicAction":"","nextUpdateTime":0,"userAction":"user_block"},"s.newsmaxfeednetwork.com":
{"dnt":false,"heuristicAction":"","nextUpdateTime":0,"userAction":"user_block"},"s.ntv.io":
{"dnt":false,"heuristicAction":"","nextUpdateTime":0,"userAction":"user_block"},"s.skimresources.com":
{"dnt":false,"heuristicAction":"","nextUpdateTime":0,"userAction":"user_block"},"s.webtrends.com":
{"dnt":false,"heuristicAction":"","nextUpdateTime":0,"userAction":"user_block"},"s-onetag.com":
{"dnt":false,"heuristicAction":"","nextUpdateTime":0,"userAction":"user_block"},"sail-horizon.com":
{"dnt":false,"heuristicAction":"","nextUpdateTime":0,"userAction":"user_block"},"scorecardresearch.com":
{"dnt":false,"heuristicAction":"","nextUpdateTime":0,"userAction":"user_block"},"script.crazyegg.com":
{"dnt":false,"heuristicAction":"","nextUpdateTime":0,"userAction":"user_block"},"sdad.guru":
{"dnt":false,"heuristicAction":"","nextUpdateTime":0,"userAction":"user_block"},"sds.livesegmentservice.com":
{"dnt":false,"heuristicAction":"","nextUpdateTime":0,"userAction":"user_block"},"searchstax.measuredsearch.com":
{"dnt":false,"heuristicAction":"","nextUpdateTime":0,"userAction":"user_block"},"secure.quantserve.com":
{"dnt":false,"heuristicAction":"","nextUpdateTime":0,"userAction":"user_block"},"segment-data.zqtk.net":
{"dnt":false,"heuristicAction":"","nextUpdateTime":0,"userAction":"user_block"},"segment.com":
{"dnt":false,"heuristicAction":"","nextUpdateTime":0,"userAction":"user_block"},"segment.io":
{"dnt":false,"heuristicAction":"","nextUpdateTime":0,"userAction":"user_block"},"service.maxymiser.net":
{"dnt":false,"heuristicAction":"","nextUpdateTime":0,"userAction":"user_block"},"servedby-buysellads.com":
{"dnt":false,"heuristicAction":"","nextUpdateTime":0,"userAction":"user_block"},"sf14g.com":
{"dnt":false,"heuristicAction":"","nextUpdateTime":0,"userAction":"user_block"},"sharethrough.com":
{"dnt":false,"heuristicAction":"","nextUpdateTime":0,"userAction":"user_block"},"simpli.fi":
{"dnt":false,"heuristicAction":"","nextUpdateTime":0,"userAction":"user_block"},"sitehelix.com":
{"dnt":false,"heuristicAction":"","nextUpdateTime":0,"userAction":"user_block"},"spotxchange.com":
{"dnt":false,"heuristicAction":"","nextUpdateTime":0,"userAction":"user_block"},"sofia.trustx.org":
{"dnt":false,"heuristicAction":"","nextUpdateTime":0,"userAction":"user_block"},"sonobi.com":
{"dnt":false,"heuristicAction":"","nextUpdateTime":0,"userAction":"user_block"},"static.hsstatic.net":
{"dnt":false,"heuristicAction":"","nextUpdateTime":0,"userAction":"user_block"},"static.parsely.com":
{"dnt":false,"heuristicAction":"","nextUpdateTime":0,"userAction":"user_block"},"static.searchstax.com":
{"dnt":false,"heuristicAction":"","nextUpdateTime":0,"userAction":"user_block"},"static.vilynx.com":
{"dnt":false,"heuristicAction":"","nextUpdateTime":0,"userAction":"user_block"},"static.yieldmo.com":
{"dnt":false,"heuristicAction":"","nextUpdateTime":0,"userAction":"user_block"},"statcounter.com":
{"dnt":false,"heuristicAction":"","nextUpdateTime":0,"userAction":"user_block"},"stats.bbc.co.uk":
{"dnt":false,"heuristicAction":"","nextUpdateTime":0,"userAction":"user_block"},"stats.kaltura.com":
{"dnt":false,"heuristicAction":"","nextUpdateTime":0,"userAction":"user_block"},"stats.pusher.com":
{"dnt":false,"heuristicAction":"","nextUpdateTime":0,"userAction":"user_block"},"stats.solidopinion.com":
{"dnt":false,"heuristicAction":"","nextUpdateTime":0,"userAction":"user_block"},"stats.storify.com":
{"dnt":false,"heuristicAction":"","nextUpdateTime":0,"userAction":"user_block"},"stats.wp.com":
{"dnt":false,"heuristicAction":"","nextUpdateTime":0,"userAction":"user_block"},"steelhousemedia.com":
{"dnt":false,"heuristicAction":"","nextUpdateTime":0,"userAction":"user_block"},"summerhamster.com":
{"dnt":false,"heuristicAction":"","nextUpdateTime":0,"userAction":"user_block"},"synapsys.us":
{"dnt":false,"heuristicAction":"","nextUpdateTime":0,"userAction":"user_block"},"taboola.com":
{"dnt":false,"heuristicAction":"","nextUpdateTime":0,"userAction":"user_block"},"tag.mtrcs.samba.tv":
{"dnt":false,"heuristicAction":"","nextUpdateTime":0,"userAction":"user_block"},"tag.researchnow.com":
{"dnt":false,"heuristicAction":"","nextUpdateTime":0,"userAction":"user_block"},"tagboard.com":
{"dnt":false,"heuristicAction":"","nextUpdateTime":0,"userAction":"user_block"},"tags.expo9.exponential.com":
{"dnt":false,"heuristicAction":"","nextUpdateTime":0,"userAction":"user_block"},"tags.mdotlabs.com":
{"dnt":false,"heuristicAction":"","nextUpdateTime":0,"userAction":"user_block"},"tags.tiqcdn.com":
{"dnt":false,"heuristicAction":"","nextUpdateTime":0,"userAction":"user_block"},"tapad.com":
{"dnt":false,"heuristicAction":"","nextUpdateTime":0,"userAction":"user_block"},"targeting.washpost.nile.works":
{"dnt":false,"heuristicAction":"","nextUpdateTime":0,"userAction":"user_block"},"tcr.tynt.com":
{"dnt":false,"heuristicAction":"","nextUpdateTime":0,"userAction":"user_block"},"tpc.googlesyndication.com":
{"dnt":false,"heuristicAction":"","nextUpdateTime":0,"userAction":"user_block"},"track.attributionapp.com":
{"dnt":false,"heuristicAction":"","nextUpdateTime":0,"userAction":"user_block"},"track.contently.com":
{"dnt":false,"heuristicAction":"","nextUpdateTime":0,"userAction":"user_block"},"track.sitehelix.com":
{"dnt":false,"heuristicAction":"","nextUpdateTime":0,"userAction":"user_block"},"track.spots.im":
{"dnt":false,"heuristicAction":"","nextUpdateTime":0,"userAction":"user_block"},"tracker.nbcuas.com":
{"dnt":false,"heuristicAction":"","nextUpdateTime":0,"userAction":"user_block"},"treasuredata.com":
{"dnt":false,"heuristicAction":"","nextUpdateTime":0,"userAction":"user_block"},"trends.revcontent.com":
{"dnt":false,"heuristicAction":"","nextUpdateTime":0,"userAction":"user_block"},"tribdss.com":
{"dnt":false,"heuristicAction":"","nextUpdateTime":0,"userAction":"user_block"},"truste.com":
{"dnt":false,"heuristicAction":"","nextUpdateTime":0,"userAction":"user_block"},"turn.com":
{"dnt":false,"heuristicAction":"","nextUpdateTime":0,"userAction":"user_block"},"tynt.com":
{"dnt":false,"heuristicAction":"","nextUpdateTime":0,"userAction":"user_block"},"udmserve.net":
{"dnt":false,"heuristicAction":"","nextUpdateTime":0,"userAction":"user_block"},"undertone.com":
{"dnt":false,"heuristicAction":"","nextUpdateTime":0,"userAction":"user_block"},"userzoom.com":
{"dnt":false,"heuristicAction":"","nextUpdateTime":0,"userAction":"user_block"},"viafoura.co":
{"dnt":false,"heuristicAction":"","nextUpdateTime":0,"userAction":"user_block"},"viafoura.net":
{"dnt":false,"heuristicAction":"","nextUpdateTime":0,"userAction":"user_block"},"visualrevenue.com":
{"dnt":false,"heuristicAction":"","nextUpdateTime":0,"userAction":"user_block"},"visualwebsiteoptimizer.com":
{"dnt":false,"heuristicAction":"","nextUpdateTime":0,"userAction":"user_block"},"vk.com":
{"dnt":false,"heuristicAction":"","nextUpdateTime":0,"userAction":"user_block"},"vo.llnwd.net":
{"dnt":false,"heuristicAction":"","nextUpdateTime":0,"userAction":"user_block"},"web-sdk.urbanairship.com":
{"dnt":false,"heuristicAction":"","nextUpdateTime":0,"userAction":"user_block"},"vcmedia.vn":
{"dnt":false,"heuristicAction":"","nextUpdateTime":0,"userAction":"user_block"},"vilynx.com":
{"dnt":false,"heuristicAction":"","nextUpdateTime":0,"userAction":"user_block"},"yldbt.com":
{"dnt":false,"heuristicAction":"","nextUpdateTime":0,"userAction":"user_block"},"zedo.com":
{"dnt":false,"heuristicAction":"","nextUpdateTime":0,"userAction":"user_block"},"zm232.com":
{"dnt":false,"heuristicAction":"","nextUpdateTime":0,"userAction":"user_block"},"zqtk.net":
{"dnt":false,"heuristicAction":"","nextUpdateTime":0,"userAction":"user_cookieblock"},"akamai.net":
{"dnt":false,"heuristicAction":"","nextUpdateTime":0,"userAction":"user_cookieblock"},"akamaihd.net":
{"dnt":false,"heuristicAction":"","nextUpdateTime":0,"userAction":"user_cookieblock"},"anvato.com":
{"dnt":false,"heuristicAction":"","nextUpdateTime":0,"userAction":"user_cookieblock"},"anvato.net":
{"dnt":false,"heuristicAction":"","nextUpdateTime":0,"userAction":"user_cookieblock"},"bbystatic.com":
{"dnt":false,"heuristicAction":"","nextUpdateTime":0,"userAction":"user_cookieblock"},"brightcove.com":
{"dnt":false,"heuristicAction":"","nextUpdateTime":0,"userAction":"user_cookieblock"},"brightcove.net":
{"dnt":false,"heuristicAction":"","nextUpdateTime":0,"userAction":"user_cookieblock"},"cloudflare.com":
{"dnt":false,"heuristicAction":"","nextUpdateTime":0,"userAction":"user_cookieblock"},"cloudfront.net":
{"dnt":false,"heuristicAction":"","nextUpdateTime":0,"userAction":"user_cookieblock"},"disqus.com":
{"dnt":false,"heuristicAction":"","nextUpdateTime":0,"userAction":"user_cookieblock"},"disqusads.com":
{"dnt":false,"heuristicAction":"","nextUpdateTime":0,"userAction":"user_cookieblock"},"gstatic.com":
{"dnt":false,"heuristicAction":"","nextUpdateTime":0,"userAction":"user_cookieblock"},"google.com":
{"dnt":false,"heuristicAction":"","nextUpdateTime":0,"userAction":"user_cookieblock"},"googleapis.com":
{"dnt":false,"heuristicAction":"","nextUpdateTime":0,"userAction":"user_cookieblock"},"googleusercontent.com":
{"dnt":false,"heuristicAction":"","nextUpdateTime":0,"userAction":"user_cookieblock"},"jwpcdn.com":
{"dnt":false,"heuristicAction":"","nextUpdateTime":0,"userAction":"user_cookieblock"},"jwplatform.com":
{"dnt":false,"heuristicAction":"","nextUpdateTime":0,"userAction":"user_cookieblock"},"jwplayer.com":
{"dnt":false,"heuristicAction":"","nextUpdateTime":0,"userAction":"user_cookieblock"},"jwpltx.com":
{"dnt":false,"heuristicAction":"","nextUpdateTime":0,"userAction":"user_cookieblock"},"licdn.com":
{"dnt":false,"heuristicAction":"","nextUpdateTime":0,"userAction":"user_cookieblock"},"lightboxcdn.com":
{"dnt":false,"heuristicAction":"","nextUpdateTime":0,"userAction":"user_cookieblock"},"livefyre.com":
{"dnt":false,"heuristicAction":"","nextUpdateTime":0,"userAction":"user_cookieblock"},"msn.com":
{"dnt":false,"heuristicAction":"","nextUpdateTime":0,"userAction":"user_cookieblock"},"nbcuni.com":               
{"dnt":false,"heuristicAction":"","nextUpdateTime":0,"userAction":"user_cookieblock"},"theplatform.com":
{"dnt":false,"heuristicAction":"","nextUpdateTime":0,"userAction":"user_cookieblock"},"twimg.com":
{"dnt":false,"heuristicAction":"","nextUpdateTime":0,"userAction":"user_cookieblock"},"twitter.com":
{"dnt":false,"heuristicAction":"","nextUpdateTime":0,"userAction":"user_cookieblock"},"typekit.com":
{"dnt":false,"heuristicAction":"","nextUpdateTime":0,"userAction":"user_cookieblock"},"univision.com":
{"dnt":false,"heuristicAction":"","nextUpdateTime":0,"userAction":"user_cookieblock"},"uvnimg.com":
{"dnt":false,"heuristicAction":"","nextUpdateTime":0,"userAction":"user_cookieblock"},"wistia.com":
{"dnt":false,"heuristicAction":"","nextUpdateTime":0,"userAction":"user_cookieblock"},"youtube.com":
{"dnt":false,"heuristicAction":"","nextUpdateTime":0,"userAction":"user_cookieblock"},"ytimg.com":
{"dnt":false,"heuristicAction":"","nextUpdateTime":0,"userAction":"user_block"}},"settings_map":{"checkForDNTPolicy":true,"disabledSites":
[],"hideBlockedElements":true,"isFirstRun":false,"migrationLevel":11,"seenComic":true,"showCounter":true,"showTrackingDomains":true,"socialWidgetReplacementEnabled":true,"webRTCIPProtection":false},"snitch_map":{"chicagotribune.com":["google.com"]}}
